APB/APB_module.v
module noWait_APB_slave#(
	parameter ADDRESS_WIDTH = 5,
	parameter DATA_WIDTH = 8
)(
	input PCLK,
	input PRESETn,
	input PSEL,
	input PENABLE,
	input [ADDRESS_WIDTH-1:0] PADDR,
	input PWRITE,
	input [DATA_WIDTH-1:0] PWDATA,
	output [DATA_WIDTH-1:0] PRDATA,
	output PREADY,
	output PSLVERR
);

// register file
reg [DATA_WIDTH-1:0] register_file [0:2**ADDRESS_WIDTH-1];
reg [DATA_WIDTH-1:0] register_out;
initial begin
       	$readmemb("PROG1.bin", register_file); 
end

assign PREADY = PSEL & PENABLE;
assign PSLVERR = PSEL & !PENABLE;

wire Write_en;
assign Write_en = PWRITE & PREADY;

wire Read_en;
assign Read_en = !PWRITE & PREADY;

always@(posedge PCLK or negedge PRESETn) begin
	if(!PRESETn) begin 
		register_out <= 0;
	end else if(Write_en) begin
		register_file[PADDR] <= PWDATA;
	end else begin
		register_out <= register_file[PADDR];
	end
end

assign PRDATA = (Read_en)? register_out : 8'bz;

endmodule

APB/APB_module_tb.v
`timescale 1ns/1ps

module tb_noWait_APB_slave;

    // Parameters
    localparam ADDRESS_WIDTH = 5;
    localparam DATA_WIDTH = 8;

    // Inputs
    reg PCLK;
    reg PRESETn;
    reg PSEL;
    reg PENABLE;
    reg [ADDRESS_WIDTH-1:0] PADDR;
    reg PWRITE;
    reg [DATA_WIDTH-1:0] PWDATA;

    // Outputs
    wire [DATA_WIDTH-1:0] PRDATA;
    wire PREADY;
    wire PSLVERR;

    // Instantiate DUT
    noWait_APB_slave #(
        .ADDRESS_WIDTH(ADDRESS_WIDTH),
        .DATA_WIDTH(DATA_WIDTH)
    ) dut (
        .PCLK(PCLK),
        .PRESETn(PRESETn),
        .PSEL(PSEL),
        .PENABLE(PENABLE),
        .PADDR(PADDR),
        .PWRITE(PWRITE),
        .PWDATA(PWDATA),
        .PRDATA(PRDATA),
        .PREADY(PREADY),
        .PSLVERR(PSLVERR)
    );


    initial begin
	$dumpfile("APB.vcd");
	$dumpvars(0, tb_noWait_APB_slave);
    end

    // Clock generation
    always #5 PCLK = ~PCLK;

    // Test sequence
    initial begin
        // Initial state
        PCLK = 1;
        PRESETn = 1;
        PSEL = 0;
        PENABLE = 0;
        PADDR = 0;
        PWRITE = 0;
        PWDATA = 0;

        // Write phase: write 8'hAA to address 0
        #12;
        PADDR = 5'd0;
        PWRITE = 1;
        PSEL = 1;
        PENABLE = 0;  // Setup phase
        PWDATA = 8'hAA;

        #10;
        PENABLE = 1;  // Access phase

        #10;
        PSEL = 0;
        PENABLE = 0;
	PWDATA = 0;

        // Read phase: read from address 0
        #20;
        PADDR = 5'd0;
        PWRITE = 0;
        PSEL = 1;
        PENABLE = 0;

        #10;
        PENABLE = 1;

        #10;
        PSEL = 0;
        PENABLE = 0;

        // End of simulation
        #20;
        $finish;
    end

endmodule

APB/APB.vcd
$date
	Tue May 27 14:05:14 2025
$end
$version
	Icarus Verilog
$end
$timescale
	1ps
$end
$scope module tb_noWait_APB_slave $end
$var wire 1 ! PSLVERR $end
$var wire 1 " PREADY $end
$var wire 8 # PRDATA [7:0] $end
$var parameter 32 $ ADDRESS_WIDTH $end
$var parameter 32 % DATA_WIDTH $end
$var reg 5 & PADDR [4:0] $end
$var reg 1 ' PCLK $end
$var reg 1 ( PENABLE $end
$var reg 1 ) PRESETn $end
$var reg 1 * PSEL $end
$var reg 8 + PWDATA [7:0] $end
$var reg 1 , PWRITE $end
$scope module dut $end
$var wire 5 - PADDR [4:0] $end
$var wire 1 ' PCLK $end
$var wire 1 ( PENABLE $end
$var wire 1 " PREADY $end
$var wire 1 ) PRESETn $end
$var wire 1 * PSEL $end
$var wire 1 ! PSLVERR $end
$var wire 8 . PWDATA [7:0] $end
$var wire 1 , PWRITE $end
$var wire 1 / Read_en $end
$var wire 1 0 Write_en $end
$var wire 8 1 PRDATA [7:0] $end
$var parameter 32 2 ADDRESS_WIDTH $end
$var parameter 32 3 DATA_WIDTH $end
$var reg 8 4 register_out [7:0] $end
$upscope $end
$upscope $end
$enddefinitions $end
$comment Show the parameter values. $end
$dumpall
b1000 3
b101 2
b1000 %
b101 $
$end
#0
$dumpvars
b11111110 4
bz 1
00
0/
b0 .
b0 -
0,
b0 +
0*
1)
0(
1'
b0 &
bz #
0"
0!
$end
#5000
0'
#10000
1'
#12000
1!
b10101010 +
b10101010 .
1*
1,
#15000
0'
#20000
1'
#22000
10
1"
0!
1(
#25000
0'
#30000
1'
#32000
00
0"
b0 +
b0 .
0(
0*
#35000
0'
#40000
b10101010 4
1'
#45000
0'
#50000
1'
#52000
1!
1*
0,
#55000
0'
#60000
1'
#62000
b10101010 #
b10101010 1
1/
1"
0!
1(
#65000
0'
#70000
1'
#72000
bz #
bz 1
0/
0"
0(
0*
